2018_univ_P_LCD/01_RTL/LCD_CTRL.v
module LCD_CTRL(clk, reset, cmd, cmd_valid, IROM_Q, IROM_rd, IROM_A, IRAM_valid, IRAM_D, IRAM_A, busy, done);
input clk;
input reset;
input [3:0] cmd;
input cmd_valid;
input [7:0] IROM_Q;
output reg IROM_rd;
output reg [5:0] IROM_A;
output reg IRAM_valid;
output reg [7:0] IRAM_D;
output reg [5:0] IRAM_A;
output busy;
output done;

reg [1:0] counter;
reg calc_done;
reg [7:0] min_val, max_val;
reg [9:0] accum_val;
reg [7:0] image [0:63];
reg [5:0] IROM_A_nxt;
reg finish_input;
reg [5:0] IRAM_CNT;
reg finish_output;
reg [2:0] S, S_nxt;

localparam S_idle = 0, S_input = 1, S_wait = 2, S_calc = 3,  S_output = 4; 

always @(posedge clk) begin
    if(reset) S = S_idle;
    else S = S_nxt;
end

always @(*) begin
    case (S)
        S_idle:
            if(!reset) begin
                S_nxt = S_input;
            end
        S_input:
            if(finish_input) begin
                S_nxt = S_wait;
            end
        S_wait:
            if(cmd_valid) begin
                if(cmd >= 5 && cmd <= 7) S_nxt = S_calc;
                else if(cmd == 0)  S_nxt = S_output;
                else S_nxt = S_wait;
            end
        S_calc:
            if(calc_done) begin
                S_nxt = S_wait;
            end
        S_output:
            if(finish_output)
                S_nxt = S_idle;
        default:
        S_nxt = S_idle;
    endcase
end

assign busy = S != S_wait;
assign done = S == S_output && S_nxt == S_idle;


wire [5:0] tmp_idx3;
wire [5:0] tmp_idx2;
wire [5:0] tmp_idx1;
wire [5:0] tmp_idx0;
wire [7:0] avg;
reg [2:0] dx, dy;
assign tmp_idx3 = dy * 8 + dx;
assign tmp_idx2 = tmp_idx3 - 1;
assign tmp_idx1 = tmp_idx2 - 7;
assign tmp_idx0 = tmp_idx1 - 1;
assign avg = accum_val /     4;

always @(posedge clk) begin
    if(reset)begin
         IROM_A <= 0;
         IROM_A_nxt <= 0;
         finish_input <= 0;
    end
    else if(S == S_input)begin
        IROM_A_nxt <= IROM_A_nxt + 1;
        IROM_A <= IROM_A_nxt;
        image[IROM_A] <= IROM_Q;
        if(IROM_A == 63) begin
            finish_input <= 1;
        end
    end
    else if(calc_done) begin
        if(cmd == 5) begin
            image[tmp_idx0] <= max_val;
            image[tmp_idx1] <= max_val;
            image[tmp_idx2] <= max_val;
            image[tmp_idx3] <= max_val;
        end
        else if(cmd == 6) begin
            image[tmp_idx0] <= min_val;
            image[tmp_idx1] <= min_val;
            image[tmp_idx2] <= min_val;
            image[tmp_idx3] <= min_val;
        end
        else if(cmd == 7) begin
            image[tmp_idx0] <= avg;
            image[tmp_idx1] <= avg;
            image[tmp_idx2] <= avg;
            image[tmp_idx3] <= avg;
        end
    end
    else if(S == S_wait && cmd_valid) begin
        if(cmd == 8)begin
            image[tmp_idx0] <= image[tmp_idx1];
            image[tmp_idx1] <= image[tmp_idx3];
            image[tmp_idx2] <= image[tmp_idx0];
            image[tmp_idx3] <= image[tmp_idx2];
        end
        else if(cmd == 9)begin
            image[tmp_idx0] <= image[tmp_idx2];
            image[tmp_idx1] <= image[tmp_idx0];
            image[tmp_idx2] <= image[tmp_idx3];
            image[tmp_idx3] <= image[tmp_idx1];
        end
        else if(cmd == 10)begin
            image[tmp_idx0] <= image[tmp_idx2];
            image[tmp_idx1] <= image[tmp_idx3];
            image[tmp_idx2] <= image[tmp_idx0];
            image[tmp_idx3] <= image[tmp_idx1];
        end
        else if(cmd == 11)begin
            image[tmp_idx0] <= image[tmp_idx1];
            image[tmp_idx1] <= image[tmp_idx0];
            image[tmp_idx2] <= image[tmp_idx3];
            image[tmp_idx3] <= image[tmp_idx2];
        end
    end
end


always @(*) begin
    if(reset) IROM_rd <= 1;
    else if(S == S_input && S_nxt == S_calc) IROM_rd <= 0;
    else IROM_rd <= IROM_rd;
end


always @(posedge clk)begin
    if(reset) begin
        dx <= 4;
        dy <= 4;
    end
    else if(S == S_wait && cmd_valid) begin
        if(cmd == 1)begin
            dy <= dy == 1 ? dy : dy - 1;
        end
        else if(cmd == 2) begin
            dy <= dy == 7 ? dy : dy + 1;
        end
        else if(cmd == 3) begin
            dx <= dx == 1 ? dx : dx - 1;
        end
        else if(cmd == 4) begin
            dx <= dx == 7 ? dx : dx + 1;
        end
    end
end



always @(posedge clk) begin
   if(reset) begin
        min_val <= 0;
        max_val <= 0;
        accum_val <= 0;
        calc_done <= 0;
        counter <= 0;
   end 
   else if(S == S_wait && cmd_valid) begin
        accum_val <= 0;
        calc_done <= 0;
   end
   else if(S == S_calc) begin
        if(counter == 0) begin
            min_val <= image[tmp_idx0];
            max_val <= image[tmp_idx0];
            accum_val = accum_val + image[tmp_idx0];
            counter <= counter + 1;
        end
        else if(counter == 1) begin
            if(image[tmp_idx1] < min_val) min_val <= image[tmp_idx1];
            if(image[tmp_idx1] > max_val) max_val <= image[tmp_idx1];
            accum_val = accum_val + image[tmp_idx1];
            counter <= counter + 1;
        end
        else if(counter == 2)begin
            if(image[tmp_idx2] < min_val) min_val <= image[tmp_idx2];
            if(image[tmp_idx2] > max_val) max_val <= image[tmp_idx2];
            accum_val = accum_val + image[tmp_idx2];
            counter <= counter + 1;
        end
        else if(counter == 3)begin
            if(image[tmp_idx3] < min_val) min_val <= image[tmp_idx3];
            if(image[tmp_idx3] > max_val) max_val <= image[tmp_idx3];
            accum_val = accum_val + image[tmp_idx3];
            counter <= counter + 1;
            calc_done <= 1;
        end
   end
end

always @(posedge clk) begin
    if(reset) begin
        IRAM_CNT <= 0;
        IRAM_A <= 0;
        IRAM_D <= 0;
        IRAM_valid <= 0;
        finish_output <= 0;
    end
    else if(S == S_output) begin
        IRAM_CNT <= IRAM_CNT + 1;
        IRAM_A <= IRAM_CNT;
        IRAM_D <= image[IRAM_CNT];
        IRAM_valid <= 1;
        if(IRAM_A == 63) begin
            finish_output <= 1;
        end
    end
    else begin
        IRAM_A <= 0;
        IRAM_CNT <= 0;
        IRAM_D <= 0;
        IRAM_valid <= 0;
        finish_output <= 0;
    end
end

endmodule

2018_univ_P_LCD/tb.v
`timescale 1ns/10ps
`define CYCLE    10.0         	        // Modify your clock period here


`define SDFFILE  "./LCD_CTRL_syn.sdf"	// Modify your sdf file name

`ifdef tb1
  `define EXPECT "./tb1_goal.dat"
  `define CMD "./cmd1.dat"
  `define IMAGE "image1.dat"
`endif

`ifdef tb2
  `define EXPECT "./tb2_goal.dat"
  `define CMD "./cmd2.dat"
  `define IMAGE "image2.dat"
`endif

`ifdef tb3
  `define EXPECT "./tb3_goal.dat"
  `define CMD "./cmd3.dat"
  `define IMAGE "image3.dat"
`endif


module test;
parameter IMAGE_N_PAT = 64;
parameter CMD_N_PAT = 46;
parameter t_reset = `CYCLE*2;


reg clk;
reg reset;
reg [6:0] err_IRAM;
reg [3:0] cmd;
reg cmd_valid;
reg [7:0]  out_mem[0:63];


wire IROM_rd;
wire [5:0] IROM_A;
wire IRAM_valid;
wire [7:0] IRAM_D;
wire [5:0] IRAM_A;
wire busy;
wire done;
wire [7:0]  IROM_Q;


integer i, j, k, l, err;

reg over;
reg   [3:0]   cmd_mem   [0:CMD_N_PAT-1];



	LCD_CTRL LCD_CTRL(.clk(clk), .reset(reset), 
		     .cmd(cmd), .cmd_valid(cmd_valid), 
                     .IROM_rd(IROM_rd), .IROM_A(IROM_A), .IROM_Q(IROM_Q), 
                     .IRAM_valid(IRAM_valid), .IRAM_D(IRAM_D), .IRAM_A(IRAM_A),
		     .busy(busy), .done(done));

	IROM  IROM_1(.IROM_rd(IROM_rd), .IROM_data(IROM_Q), .IROM_addr(IROM_A), .clk(clk), .reset(reset));

	IRAM IRAM_1 (.clk(clk), .IRAM_data(IRAM_D), .IRAM_addr(IRAM_A), .IRAM_valid(IRAM_valid));


//initial $sdf_annotate(`SDFFILE, top);

`ifdef SDF
	initial $sdf_annotate(`SDFFILE, LCD_CTRL);
`endif

initial	$readmemh (`CMD,    cmd_mem);
initial	$readmemh (`EXPECT, out_mem);

initial begin

// $fsdbDumpfile("LCD_CTRL.fsdb");
// $fsdbDumpvars;
// $fsdbDumpMDA;
end
initial begin
    $dumpfile("LCD_CTRL.vcd");  // VCD 波形文件
    $dumpvars(0, LCD_CTRL);         // 记录所有变量

	// for (i = 0; i < 64; i = i + 1) begin
    //     $dumpvars(0, LCD_CTRL.image[i]); // 记录 image 数组的所有值
    // end
end





initial begin
   clk         = 1'b0;
   reset       = 1'b0;
   over	       = 1'b0;
   l	       = 0;
   err         = 0;   
end

always begin #(`CYCLE/2) clk = ~clk; end

initial begin
   @(negedge clk)  reset = 1'b1;
   #t_reset        reset = 1'b0;
                                  
end  

            
 always @(negedge clk)
begin

	begin
	if (l < CMD_N_PAT)
	begin
		if(!busy) 
		begin
        	cmd = cmd_mem[l];
        	cmd_valid = 1'b1;
		l=l+1;
		end  
		else
		cmd_valid = 1'b0;
	end
	else
	begin
		l=l;
		cmd_valid = 1'b0;
	end
	end
end


initial @(posedge done) 
begin
   for(k=0;k<64;k=k+1)begin
         if( IRAM_1.IRAM_M[k] !== out_mem[k]) 
		begin
         	$display("ERROR at %d:output %h !=expect %h ",k, IRAM_1.IRAM_M[k], out_mem[k]);
         	err = err+1 ;
		end
         else if ( out_mem[k] === 8'dx)
                begin
                $display("ERROR at %d:output %h !=expect %h ",k, IRAM_1.IRAM_M[k], out_mem[k]);
		err=err+1;
                end   
 over=1'b1;
end
        begin
	if (err === 0 &&  over===1'b1  )  begin
	            $display("All data have been generated successfully!\n");
	            $display("-------------------PASS-------------------\n");
		    #10 $finish;
	         end
	         else if( over===1'b1 )
		 begin 
	            $display("There are %d errors!\n", err);
	            $display("---------------------------------------------\n");
		    #10 $finish;
         	 end
	
	end
end

endmodule


//-----------------------------------------------------------------------
//-----------------------------------------------------------------------
module IROM (IROM_rd, IROM_data, IROM_addr, clk, reset);
input		IROM_rd;
input	[5:0] 	IROM_addr;
output	[7:0]	IROM_data;
input		clk, reset;

reg [7:0] sti_M [0:63];
integer i;

reg	[7:0]	IROM_data;

initial begin
	@ (negedge reset) $readmemb (`IMAGE , sti_M);
	end

always@(negedge clk) 
	if (IROM_rd) IROM_data <= sti_M[IROM_addr];
	
endmodule



//-----------------------------------------------------------------------
//-----------------------------------------------------------------------

module IRAM (IRAM_valid, IRAM_data, IRAM_addr, clk);
input		IRAM_valid;
input	[5:0] 	IRAM_addr;
input	[7:0]	IRAM_data;
input		clk;

reg [7:0] IRAM_M [0:63];
integer i;

initial begin
	for (i=0; i<=63; i=i+1) IRAM_M[i] = 0;
end

always@(negedge clk) 
	if (IRAM_valid) IRAM_M[ IRAM_addr ] <= IRAM_data;

endmodule

2018_univ_P_LCD/01_RTL/LCD_CTRL.vcd
$date
	Thu Mar 20 11:53:47 2025
$end

$version
	Synopsys VCS version T-2022.06_Full64
$end

$timescale
	10ps
$end

$comment Csum: 1 d94b1d42eb1db87e $end


$scope module test $end

$scope module LCD_CTRL $end
$var wire 1 ! clk $end
$var wire 1 " reset $end
$var wire 4 # cmd [3:0] $end
$var wire 1 $ cmd_valid $end
$var wire 8 % IROM_Q [7:0] $end
$var reg 1 & IROM_rd $end
$var reg 6 ' IROM_A [5:0] $end
$var reg 1 ( IRAM_valid $end
$var reg 8 ) IRAM_D [7:0] $end
$var reg 6 * IRAM_A [5:0] $end
$var wire 1 + busy $end
$var wire 1 , done $end
$var reg 2 - counter [1:0] $end
$var reg 1 . calc_done $end
$var reg 8 / min_val [7:0] $end
$var reg 8 0 max_val [7:0] $end
$var reg 10 1 accum_val [9:0] $end
$var reg 6 2 IROM_A_nxt [5:0] $end
$var reg 1 3 finish_input $end
$var reg 6 4 IRAM_CNT [5:0] $end
$var reg 1 5 finish_output $end
$var reg 3 6 S [2:0] $end
$var reg 3 7 S_nxt [2:0] $end
$var wire 6 8 tmp_idx3 [5:0] $end
$var wire 6 9 tmp_idx2 [5:0] $end
$var wire 6 : tmp_idx1 [5:0] $end
$var wire 6 ; tmp_idx0 [5:0] $end
$var wire 8 < avg [7:0] $end
$var reg 3 = dx [2:0] $end
$var reg 3 > dy [2:0] $end
$upscope $end

$upscope $end

$enddefinitions $end

#0
$dumpvars
x(
x&
x.
x3
x5
bxxxxxx *
bxxxxxx 4
bxxxxxxxx )
bxxxxxx '
bxxxxxx 2
bxxx 6
b000 7
bxxxxxxxxxx 1
bxxxxxxxx <
bxx -
bxxx =
bxxx >
bxxxxxxxx 0
bxxxxxxxx /
bxxxxxx ;
bxxxxxx :
bxxxxxx 9
bxxxxxx 8
0!
x+
x,
0"
bxxxx #
0$
bxxxxxxxx %
$end
#500
1!
b000 6
0,
1+
b001 7
b000000 *
b000000 4
b00000000 )
0(
05
#1000
0!
1"
1&
#1500
1!
b000000 '
b000000 2
03
b100 =
b100100 8
b100011 9
b011100 :
b011011 ;
b100 >
b00000000 /
b00000000 0
b0000000000 1
b00000000 <
0.
b00 -
#2000
0!
#2500
1!
#3000
0"
0!
b11001101 %
#3500
1!
b001 6
b000001 2
#4000
0!
#4500
1!
b000010 2
b000001 '
#5000
0!
b00010010 %
#5500
1!
b000011 2
b000010 '
#6000
0!
b11110011 %
#6500
1!
b000100 2
b000011 '
#7000
0!
b00110011 %
#7500
1!
b000101 2
b000100 '
#8000
0!
b10000111 %
#8500
1!
b000110 2
b000101 '
#9000
0!
b00100100 %
#9500
1!
b000111 2
b000110 '
#10000
0!
b01111010 %
#10500
1!
b001000 2
b000111 '
#11000
0!
b01011001 %
#11500
1!
b001001 2
b001000 '
#12000
0!
b10000000 %
#12500
1!
b001010 2
b001001 '
#13000
0!
b01000001 %
#13500
1!
b001011 2
b001010 '
#14000
0!
b00110110 %
#14500
1!
b001100 2
b001011 '
#15000
0!
b01110001 %
#15500
1!
b001101 2
b001100 '
#16000
0!
b10111111 %
#16500
1!
b001110 2
b001101 '
#17000
0!
b10101110 %
#17500
1!
b001111 2
b001110 '
#18000
0!
b11111111 %
#18500
1!
b010000 2
b001111 '
#19000
0!
b01100110 %
#19500
1!
b010001 2
b010000 '
#20000
0!
b01001001 %
#20500
1!
b010010 2
b010001 '
#21000
0!
b00100111 %
#21500
1!
b010011 2
b010010 '
#22000
0!
b10010100 %
#22500
1!
b010100 2
b010011 '
#23000
0!
b01111001 %
#23500
1!
b010101 2
b010100 '
#24000
0!
b00111010 %
#24500
1!
b010110 2
b010101 '
#25000
0!
b10111000 %
#25500
1!
b010111 2
b010110 '
#26000
0!
b01101001 %
#26500
1!
b011000 2
b010111 '
#27000
0!
b11010010 %
#27500
1!
b011001 2
b011000 '
#28000
0!
b10100111 %
#28500
1!
b011010 2
b011001 '
#29000
0!
b00111011 %
#29500
1!
b011011 2
b011010 '
#30000
0!
b00110000 %
#30500
1!
b011100 2
b011011 '
#31000
0!
b10011000 %
#31500
1!
b011101 2
b011100 '
#32000
0!
b00011000 %
#32500
1!
b011110 2
b011101 '
#33000
0!
b00100101 %
#33500
1!
b011111 2
b011110 '
#34000
0!
b11011010 %
#34500
1!
b100000 2
b011111 '
#35000
0!
b00100000 %
#35500
1!
b100001 2
b100000 '
#36000
0!
b00100010 %
#36500
1!
b100010 2
b100001 '
#37000
0!
b00111000 %
#37500
1!
b100011 2
b100010 '
#38000
0!
b11000110 %
#38500
1!
b100100 2
b100011 '
#39000
0!
b00000000 %
#39500
1!
b100101 2
b100100 '
#40000
0!
b00100110 %
#40500
1!
b100110 2
b100101 '
#41000
0!
b10000011 %
#41500
1!
b100111 2
b100110 '
#42000
0!
b01101000 %
#42500
1!
b101000 2
b100111 '
#43000
0!
b00100101 %
#43500
1!
b101001 2
b101000 '
#44000
0!
b11010111 %
#44500
1!
b101010 2
b101001 '
#45000
0!
b00001010 %
#45500
1!
b101011 2
b101010 '
#46000
0!
b11100011 %
#46500
1!
b101100 2
b101011 '
#47000
0!
b01000001 %
#47500
1!
b101101 2
b101100 '
#48000
0!
b00100101 %
#48500
1!
b101110 2
b101101 '
#49000
0!
b11100001 %
#49500
1!
b101111 2
b101110 '
#50000
0!
b00110111 %
#50500
1!
b110000 2
b101111 '
#51000
0!
b10000000 %
#51500
1!
b110001 2
b110000 '
#52000
0!
b10000111 %
#52500
1!
b110010 2
b110001 '
#53000
0!
b10010100 %
#53500
1!
b110011 2
b110010 '
#54000
0!
b10101111 %
#54500
1!
b110100 2
b110011 '
#55000
0!
b01110111 %
#55500
1!
b110101 2
b110100 '
#56000
0!
b00101000 %
#56500
1!
b110110 2
b110101 '
#57000
0!
b11101100 %
#57500
1!
b110111 2
b110110 '
#58000
0!
b01010110 %
#58500
1!
b111000 2
b110111 '
#59000
0!
b01000111 %
#59500
1!
b111001 2
b111000 '
#60000
0!
b01011010 %
#60500
1!
b111010 2
b111001 '
#61000
0!
b00110111 %
#61500
1!
b111011 2
b111010 '
#62000
0!
b11000001 %
#62500
1!
b111100 2
b111011 '
#63000
0!
b00000100 %
#63500
1!
b111101 2
b111100 '
#64000
0!
b00010011 %
#64500
1!
b111110 2
b111101 '
#65000
0!
b01100110 %
#65500
1!
b111111 2
b111110 '
#66000
0!
b11111111 %
#66500
1!
b000000 2
b111111 '
#67000
0!
b11000000 %
#67500
1!
b000001 2
b000000 '
13
b010 7
#68000
0!
b11001101 %
#68500
1!
b010 6
0+
#69000
0!
b0100 #
1$
#69500
1!
b101 =
b100101 8
b100100 9
b011101 :
b011100 ;
#70000
0!
#70500
1!
b110 =
b100110 8
b100101 9
b011110 :
b011101 ;
#71000
0!
b0110 #
b011 7
#71500
1!
b011 6
1+
b0000100101 1
b00001001 <
b00100101 /
b00100101 0
b01 -
#72000
0!
0$
#72500
1!
b0011111111 1
b00111111 <
b11011010 0
b10 -
#73000
0!
#73500
1!
b0110000010 1
b01100000 <
b11 -
#74000
0!
#74500
1!
b0111101010 1
b01111010 <
b00 -
1.
b010 7
#75000
0!
#75500
1!
b010 6
0+
#76000
0!
b0100 #
1$
#76500
1!
b111 =
b100111 8
b100110 9
b011111 :
b011110 ;
b0000000000 1
b00000000 <
0.
#77000
0!
b1001 #
#77500
1!
#78000
0!
b0100 #
#78500
1!
#79000
0!
b1011 #
#79500
1!
#80000
0!
b0001 #
#80500
1!
b011 >
b011111 8
b011110 9
b010111 :
b010110 ;
#81000
0!
b0111 #
b011 7
#81500
1!
b011 6
1+
b0001101001 1
b00011010 <
b01101001 /
b01101001 0
b01 -
#82000
0!
0$
#82500
1!
b0100111011 1
b01001110 <
b11010010 0
b10 -
#83000
0!
#83500
1!
b0101100000 1
b01011000 <
b00100101 /
b11 -
#84000
0!
#84500
1!
b0110000101 1
b01100001 <
b00 -
1.
b010 7
#85000
0!
#85500
1!
b010 6
0+
#86000
0!
b0011 #
1$
#86500
1!
b110 =
b011110 8
b011101 9
b010110 :
b010101 ;
b0000000000 1
b00000000 <
0.
#87000
0!
b1000 #
#87500
1!
#88000
0!
b0001 #
#88500
1!
b010 >
b010110 8
b010101 9
b001110 :
b001101 ;
#89000
0!
b0101 #
b011 7
#89500
1!
b011 6
1+
b0010101110 1
b00101011 <
b10101110 /
b10101110 0
b01 -
#90000
0!
0$
#90500
1!
b0110101101 1
b01101011 <
b11111111 0
b10 -
#91000
0!
#91500
1!
b1000001110 1
b10000011 <
b01100001 /
b11 -
#92000
0!
#92500
1!
b1001101111 1
b10011011 <
b00 -
1.
b010 7
#93000
0!
#93500
1!
b010 6
0+
#94000
0!
b0011 #
1$
#94500
1!
b101 =
b010101 8
b010100 9
b001101 :
b001100 ;
b0000000000 1
b00000000 <
0.
#95000
0!
b1010 #
#95500
1!
#96000
0!
b0001 #
#96500
1!
b001 >
b001101 8
b001100 9
b000101 :
b000100 ;
#97000
0!
b1001 #
#97500
1!
#98000
0!
b0001 #
#98500
1!
#99000
0!
b1010 #
#99500
1!
#100000
0!
b0001 #
#100500
1!
#101000
0!
b1011 #
#101500
1!
#102000
0!
b1010 #
#102500
1!
#103000
0!
b0010 #
#103500
1!
b010 >
b010101 8
b010100 9
b001101 :
b001100 ;
#104000
0!
b0011 #
#104500
1!
b100 =
b010100 8
b010011 9
b001100 :
b001011 ;
#105000
0!
b0010 #
#105500
1!
b011 >
b011100 8
b011011 9
b010100 :
b010011 ;
#106000
0!
b1001 #
#106500
1!
#107000
0!
b0011 #
#107500
1!
b011 =
b011011 8
b011010 9
b010011 :
b010010 ;
#108000
0!
b0101 #
b011 7
#108500
1!
b011 6
1+
b0010010100 1
b00100101 <
b10010100 /
b10010100 0
b01 -
#109000
0!
0$
#109500
1!
b0100101100 1
b01001011 <
b10011000 0
b10 -
#110000
0!
#110500
1!
b0101011100 1
b01010111 <
b00110000 /
b11 -
#111000
0!
#111500
1!
b0101110100 1
b01011101 <
b00011000 /
b00 -
1.
b010 7
#112000
0!
#112500
1!
b010 6
0+
#113000
0!
b0010 #
1$
#113500
1!
b100 >
b100011 8
b100010 9
b011011 :
b011010 ;
b0000000000 1
b00000000 <
0.
#114000
0!
b1010 #
#114500
1!
#115000
0!
b0011 #
#115500
1!
b010 =
b100010 8
b100001 9
b011010 :
b011001 ;
#116000
0!
b0110 #
b011 7
#116500
1!
b011 6
1+
b0000111011 1
b00001110 <
b00111011 /
b00111011 0
b01 -
#117000
0!
0$
#117500
1!
b0100000001 1
b01000000 <
b11000110 0
b10 -
#118000
0!
#118500
1!
b0100111001 1
b01001110 <
b00111000 /
b11 -
#119000
0!
#119500
1!
b0111010001 1
b01110100 <
b00 -
1.
b010 7
#120000
0!
#120500
1!
b010 6
0+
#121000
0!
b0011 #
1$
#121500
1!
b001 =
b100001 8
b100000 9
b011001 :
b011000 ;
b0000000000 1
b00000000 <
0.
#122000
0!
b1000 #
#122500
1!
#123000
0!
b0010 #
#123500
1!
b101 >
b101001 8
b101000 9
b100001 :
b100000 ;
#124000
0!
b1011 #
#124500
1!
#125000
0!
b0100 #
#125500
1!
b010 =
b101010 8
b101001 9
b100010 :
b100001 ;
#126000
0!
b0111 #
b011 7
#126500
1!
b011 6
1+
b0010100111 1
b00101001 <
b10100111 /
b10100111 0
b01 -
#127000
0!
0$
#127500
1!
b0011011111 1
b00110111 <
b00111000 /
b10 -
#128000
0!
#128500
1!
b0110110110 1
b01101101 <
b11010111 0
b11 -
#129000
0!
#129500
1!
b1010011001 1
b10100110 <
b11100011 0
b00 -
1.
b010 7
#130000
0!
#130500
1!
b010 6
0+
#131000
0!
b0010 #
1$
#131500
1!
b110 >
b110010 8
b110001 9
b101010 :
b101001 ;
b0000000000 1
b00000000 <
0.
#132000
0!
#132500
1!
b111 >
b111010 8
b111001 9
b110010 :
b110001 ;
#133000
0!
b1001 #
#133500
1!
#134000
0!
b0010 #
#134500
1!
#135000
0!
b0100 #
#135500
1!
b011 =
b111011 8
b111010 9
b110011 :
b110010 ;
#136000
0!
b1010 #
#136500
1!
#137000
0!
b1001 #
#137500
1!
#138000
0!
b0000 #
b100 7
#138500
1!
b100 6
1+
b000001 4
b11001101 )
1(
#139000
0!
0$
#139500
1!
b000010 4
b000001 *
b00010010 )
#140000
0!
#140500
1!
b000011 4
b000010 *
b11110011 )
#141000
0!
#141500
1!
b000100 4
b000011 *
b00110011 )
#142000
0!
#142500
1!
b000101 4
b000100 *
b10000111 )
#143000
0!
#143500
1!
b000110 4
b000101 *
b00111010 )
#144000
0!
#144500
1!
b000111 4
b000110 *
b01111010 )
#145000
0!
#145500
1!
b001000 4
b000111 *
b01011001 )
#146000
0!
#146500
1!
b001001 4
b001000 *
b10000000 )
#147000
0!
#147500
1!
b001010 4
b001001 *
b01000001 )
#148000
0!
#148500
1!
b001011 4
b001010 *
b00110110 )
#149000
0!
#149500
1!
b001100 4
b001011 *
b01110001 )
#150000
0!
#150500
1!
b001101 4
b001100 *
b00100100 )
#151000
0!
#151500
1!
b001110 4
b001101 *
b11111111 )
#152000
0!
#152500
1!
b001111 4
b001110 *
#153000
0!
#153500
1!
b010000 4
b001111 *
b01100110 )
#154000
0!
#154500
1!
b010001 4
b010000 *
b01001001 )
#155000
0!
#155500
1!
b010010 4
b010001 *
b00100111 )
#156000
0!
#156500
1!
b010011 4
b010010 *
b10011000 )
#157000
0!
#157500
1!
b010100 4
b010011 *
#158000
0!
#158500
1!
b010101 4
b010100 *
b01111001 )
#159000
0!
#159500
1!
b010110 4
b010101 *
b11111111 )
#160000
0!
#160500
1!
b010111 4
b010110 *
#161000
0!
#161500
1!
b011000 4
b010111 *
b01100001 )
#162000
0!
#162500
1!
b011001 4
b011000 *
b00111000 )
#163000
0!
#163500
1!
b011010 4
b011001 *
#164000
0!
#164500
1!
b011011 4
b011010 *
#165000
0!
#165500
1!
b011100 4
b011011 *
b00000000 )
#166000
0!
#166500
1!
b011101 4
b011100 *
b10111111 )
#167000
0!
#167500
1!
b011110 4
b011101 *
b10111000 )
#168000
0!
#168500
1!
b011111 4
b011110 *
b00100101 )
#169000
0!
#169500
1!
b100000 4
b011111 *
b01100001 )
#170000
0!
#170500
1!
b100001 4
b100000 *
b00100010 )
#171000
0!
#171500
1!
b100010 4
b100001 *
b10100110 )
#172000
0!
#172500
1!
b100011 4
b100010 *
#173000
0!
#173500
1!
b100100 4
b100011 *
b10011000 )
#174000
0!
#174500
1!
b100101 4
b100100 *
b00100110 )
#175000
0!
#175500
1!
b100110 4
b100101 *
b00100101 )
#176000
0!
#176500
1!
b100111 4
b100110 *
b00100000 )
#177000
0!
#177500
1!
b101000 4
b100111 *
b00100101 )
#178000
0!
#178500
1!
b101001 4
b101000 *
b00001010 )
#179000
0!
#179500
1!
b101010 4
b101001 *
b10100110 )
#180000
0!
#180500
1!
b101011 4
b101010 *
#181000
0!
#181500
1!
b101100 4
b101011 *
b01000001 )
#182000
0!
#182500
1!
b101101 4
b101100 *
b00100101 )
#183000
0!
#183500
1!
b101110 4
b101101 *
b11100001 )
#184000
0!
#184500
1!
b101111 4
b101110 *
b00110111 )
#185000
0!
#185500
1!
b110000 4
b101111 *
b10000000 )
#186000
0!
#186500
1!
b110001 4
b110000 *
b10000111 )
#187000
0!
#187500
1!
b110010 4
b110001 *
b00110111 )
#188000
0!
#188500
1!
b110011 4
b110010 *
b10010100 )
#189000
0!
#189500
1!
b110100 4
b110011 *
b10101111 )
#190000
0!
#190500
1!
b110101 4
b110100 *
b00101000 )
#191000
0!
#191500
1!
b110110 4
b110101 *
b11101100 )
#192000
0!
#192500
1!
b110111 4
b110110 *
b01010110 )
#193000
0!
#193500
1!
b111000 4
b110111 *
b01000111 )
#194000
0!
#194500
1!
b111001 4
b111000 *
b01011010 )
#195000
0!
#195500
1!
b111010 4
b111001 *
b11000001 )
#196000
0!
#196500
1!
b111011 4
b111010 *
b01110111 )
#197000
0!
#197500
1!
b111100 4
b111011 *
b00000100 )
#198000
0!
#198500
1!
b111101 4
b111100 *
b00010011 )
#199000
0!
#199500
1!
b111110 4
b111101 *
b01100110 )
#200000
0!
#200500
1!
b111111 4
b111110 *
b11111111 )
#201000
0!
#201500
1!
b000000 4
b111111 *
b11000000 )
#202000
0!
#202500
1!
b000001 4
b000000 *
b11001101 )
15
b000 7
1,
